helpers/__init__.py
helpers/tester_as_class.py
helpers/tester_as_function.py
helpers/api/__init__.py
helpers/api/google/__init__.py
helpers/api/google/youtube.py
helpers/api/naver/__init__.py
helpers/api/naver/books.py
helpers/api/naver/sens.py
helpers/django/__init__.py
helpers/django/admin/__init__.py
helpers/django/admin/utils.py
helpers/python/__init__.py
helpers/python/converter.py
helpers/python/dict/__init__.py
helpers/python/dict/utils.py
helpers/python/dict/validator.py
helpers/python/key/__init__.py
helpers/python/key/generator.py
helpers/rest_framework/__init__.py
helpers/rest_framework/authentication.py
helpers/rest_framework/permissions.py
helpers/rest_framework/request_manager.py
helpers_takemyhands-0.0.24.dist-info/DESCRIPTION.rst
helpers_takemyhands-0.0.24.dist-info/METADATA
helpers_takemyhands-0.0.24.dist-info/RECORD
helpers_takemyhands-0.0.24.dist-info/WHEEL
helpers_takemyhands-0.0.24.dist-info/metadata.json
helpers_takemyhands-0.0.24.dist-info/top_level.txt
